beagleeditor/__init__.py
beagleeditor/autocomplete.py
beagleeditor/beagleeditor.py
beagleeditor/marketplace.py
beagleeditor/splash.py
beagleeditor/syntax.py
beagleeditor/wizard.py
beagleeditor/plugins/Terminal.py
BeagleEditor-3.0.1.dist-info/LICENSE
BeagleEditor-3.0.1.dist-info/METADATA
BeagleEditor-3.0.1.dist-info/WHEEL
BeagleEditor-3.0.1.dist-info/top_level.txt
BeagleEditor-3.0.1.dist-info/RECORD
