Metadata-Version: 2.1
Name: BeagleEditor
Version: 3.0.1
Summary: A minimal code editor
Author-email: Mani Arasteh <mani.arasteh92@gmail.com>
Project-URL: Homepage, https://maarasteh.github.io/beagleeditor
Project-URL: GitHub, https://github.com/MaArasteh/beagleeditor
Project-URL: Issues, https://github.com/MaArasteh/beagleeditor/issues
Classifier: Programming Language :: Python :: 3
Classifier: License :: OSI Approved :: MIT License
Classifier: Operating System :: OS Independent
Requires-Python: >=3.8
License-File: LICENSE
